LICENSE
MANIFEST.in
README.rst
setup.py
garment/__init__.py
garment/config.py
garment/deploy.py
garment/release.py
garment/stages.py
garment/vagrant.py
garment.egg-info/PKG-INFO
garment.egg-info/SOURCES.txt
garment.egg-info/dependency_links.txt
garment.egg-info/requires.txt
garment.egg-info/top_level.txt
scripts/deploy